kafthon/__init__.py
kafthon/__init__.pyc
kafthon/event_subscription.py
kafthon/events.py
kafthon/exceptions.py
kafthon/field.py
kafthon/field_mapping.py
kafthon/kafthon.py
kafthon/registry.py
kafthon/runnables.py
kafthon/runners.py
kafthon/serializers.py
kafthon/start_runnable.py
kafthon/utils.py
kafthon/hubs/__init__.py
kafthon/hubs/base_hub.py
kafthon/hubs/kafka_hub.py
kafthon/hubs/local_hub.py
Kafthon-0.0.1.dist-info/METADATA
Kafthon-0.0.1.dist-info/WHEEL
Kafthon-0.0.1.dist-info/top_level.txt
Kafthon-0.0.1.dist-info/RECORD
