Metadata-Version: 2.1
Name: Kafthon
Version: 0.0.1
Summary: High level Python wrapper for Kafka
Home-page: https://github.com/aabversteeg/kafthon
Author: B. Versteeg
Author-email: a.b.versteeg@gmail.com
License: UNKNOWN
Platform: UNKNOWN
Classifier: Programming Language :: Python :: 3
Classifier: Operating System :: OS Independent
Requires-Dist: docker
Requires-Dist: kafka-python
Requires-Dist: msgpack
Requires-Dist: typeguard
Requires-Dist: temporenc
